purple_auth_client.py
purple_auth_client-1.0.2.dist-info/WHEEL
purple_auth_client-1.0.2.dist-info/METADATA
purple_auth_client-1.0.2.dist-info/RECORD
