Metadata-Version: 2.1
Name: purple-auth-client
Version: 1.0.2
Summary: Client library for Purple Auth
License: MIT
Author: Rick Henry
Author-email: rickhenry@rickhenry.dev
Requires-Python: >=3.7,<4.0
Classifier: License :: OSI Approved :: MIT License
Classifier: Programming Language :: Python :: 3
Classifier: Programming Language :: Python :: 3.10
Classifier: Programming Language :: Python :: 3.7
Classifier: Programming Language :: Python :: 3.8
Classifier: Programming Language :: Python :: 3.9
Requires-Dist: aiohttp (>=3.8.1,<4.0.0)
Requires-Dist: python-jwt (>=3.3.0,<4.0.0)
